simple_geoip/__init__.py
simple_geoip/exceptions.py
simple_geoip/geoip.py
simple_geoip/settings.py
simple_geoip-0.1.1.dist-info/METADATA
simple_geoip-0.1.1.dist-info/WHEEL
simple_geoip-0.1.1.dist-info/top_level.txt
simple_geoip-0.1.1.dist-info/RECORD
